<?xml version="1.0" encoding="utf-8" ?>
<Defs>
	<AlienRace.AlienBackstoryDef>
		<defName>NandroidGeneric</defName>
		<title>Nandroid</title>
		<titleShort>Nandroid</titleShort>
		<baseDesc>{PAWN_nameDef} is a Sterling brand Nandroid that was slated to go to an Urbworld, but somehow found themselves on the Rim.</baseDesc>
		<bodyTypeFemale>Female</bodyTypeFemale>
		<shuffleable>True</shuffleable>
		<slot>Childhood</slot>
		<spawnCategories>
			<li>NandroidGeneral</li>
			<li>BadGurlz</li>
			<li>NandroidSoldiers</li>
		</spawnCategories>
		<skillGains>
          <li>
            <key>Shooting</key>
            <value>1</value>
          </li>
          <li>
            <key>Melee</key>
            <value>1</value>
          </li>
		  <li>
            <key>Construction</key>
            <value>2</value>
          </li>
		  <li>
            <key>Mining</key>
            <value>1</value>
          </li>
		  <li>
            <key>Cooking</key>
            <value>5</value>
          </li>
		  <li>
            <key>Plants</key>
            <value>1</value>
          </li>
		  <li>
            <key>Animals</key>
            <value>1</value>
          </li>
		  <li>
            <key>Crafting</key>
            <value>2</value>
          </li>
		  <li>
            <key>Artistic</key>
            <value>1</value>
          </li>
		  <li>
            <key>Medicine</key>
            <value>2</value>
          </li>
		  <li>
            <key>Social</key>
            <value>5</value>
          </li>
		  <li>
            <key>Intellectual</key>
            <value>2</value>
          </li>
        </skillGains>
	</AlienRace.AlienBackstoryDef>
	
	<AlienRace.AlienBackstoryDef>
		<defName>NandroidOffbrand</defName>
		<title>Off-Brand Nandroid</title>
		<titleShort>Off-Brand Nan</titleShort>
		<baseDesc>{PAWN_nameDef} is an off-brand Nandroid-like robotic maid that was slated to go to an Urbworld, but somehow found themselves on the Rim.</baseDesc>
		<bodyTypeFemale>Female</bodyTypeFemale>
		<shuffleable>True</shuffleable>
		<slot>Childhood</slot>
		<spawnCategories>
			<li>NandroidGeneral</li>
			<li>BadGurlz</li>
			<li>NandroidSoldiers</li>
		</spawnCategories>
		<skillGains>
          <li>
            <key>Shooting</key>
            <value>1</value>
          </li>
          <li>
            <key>Melee</key>
            <value>1</value>
          </li>
		  <li>
            <key>Construction</key>
            <value>2</value>
          </li>
		  <li>
            <key>Mining</key>
            <value>1</value>
          </li>
		  <li>
            <key>Cooking</key>
            <value>5</value>
          </li>
		  <li>
            <key>Plants</key>
            <value>1</value>
          </li>
		  <li>
            <key>Animals</key>
            <value>1</value>
          </li>
		  <li>
            <key>Crafting</key>
            <value>2</value>
          </li>
		  <li>
            <key>Artistic</key>
            <value>1</value>
          </li>
		  <li>
            <key>Medicine</key>
            <value>2</value>
          </li>
		  <li>
            <key>Social</key>
            <value>5</value>
          </li>
		  <li>
            <key>Intellectual</key>
            <value>2</value>
          </li>
        </skillGains>
	</AlienRace.AlienBackstoryDef>
	
	<AlienRace.AlienBackstoryDef>
		<defName>NandroidHighGrade</defName>
		<title>High-Grade Nandroid</title>
		<titleShort>High-Grade Nan</titleShort>
		<baseDesc>{PAWN_nameDef} is a Sterling brand Nandroid that was built with higher specifications befitting to their Glitterworld destination, but somehow found themselves on the Rim.</baseDesc>
		<bodyTypeFemale>Female</bodyTypeFemale>
		<shuffleable>True</shuffleable>
		<slot>Childhood</slot>
		<spawnCategories>
			<li>NandroidGeneral</li>
			<li>NandroidSoldiers</li>
		</spawnCategories>
		<skillGains>
          <li>
            <key>Shooting</key>
            <value>1</value>
          </li>
          <li>
            <key>Melee</key>
            <value>1</value>
          </li>
		  <li>
            <key>Construction</key>
            <value>2</value>
          </li>
		  <li>
            <key>Mining</key>
            <value>1</value>
          </li>
		  <li>
            <key>Cooking</key>
            <value>6</value>
          </li>
		  <li>
            <key>Plants</key>
            <value>1</value>
          </li>
		  <li>
            <key>Animals</key>
            <value>1</value>
          </li>
		  <li>
            <key>Crafting</key>
            <value>2</value>
          </li>
		  <li>
            <key>Artistic</key>
            <value>2</value>
          </li>
		  <li>
            <key>Medicine</key>
            <value>3</value>
          </li>
		  <li>
            <key>Social</key>
            <value>6</value>
          </li>
		  <li>
            <key>Intellectual</key>
            <value>3</value>
          </li>
        </skillGains>
	</AlienRace.AlienBackstoryDef>
	
	<AlienRace.AlienBackstoryDef>
		<defName>NandroidIndustrial</defName>
		<title>Industrial Nandroid</title>
		<titleShort>Industrial Nan</titleShort>
		<baseDesc>{PAWN_nameDef} is a Sterling brand Nandroid whose specifications are fit for heavy industry, but somehow found themselves on the Rim.</baseDesc>
		<bodyTypeFemale>Female</bodyTypeFemale>
		<shuffleable>True</shuffleable>
		<slot>Childhood</slot>
		<spawnCategories>
			<li>NandroidGeneral</li>
			<li>BadGurlz</li>
			<li>NandroidSoldiers</li>
		</spawnCategories>
		<skillGains>
          <li>
            <key>Shooting</key>
            <value>1</value>
          </li>
          <li>
            <key>Melee</key>
            <value>1</value>
          </li>
		  <li>
            <key>Construction</key>
            <value>3</value>
          </li>
		  <li>
            <key>Mining</key>
            <value>2</value>
          </li>
		  <li>
            <key>Cooking</key>
            <value>5</value>
          </li>
		  <li>
            <key>Plants</key>
            <value>2</value>
          </li>
		  <li>
            <key>Animals</key>
            <value>2</value>
          </li>
		  <li>
            <key>Crafting</key>
            <value>3</value>
          </li>
		  <li>
            <key>Artistic</key>
            <value>1</value>
          </li>
		  <li>
            <key>Medicine</key>
            <value>2</value>
          </li>
		  <li>
            <key>Social</key>
            <value>5</value>
          </li>
		  <li>
            <key>Intellectual</key>
            <value>2</value>
          </li>
        </skillGains>
	</AlienRace.AlienBackstoryDef>
	
	<AlienRace.AlienBackstoryDef>
		<defName>NandroidExperimental</defName>
		<title>Experimental Nandroid</title>
		<titleShort>Test Nandroid</titleShort>
		<baseDesc>{PAWN_nameDef} is an experimental model Sterling brand Nandroid that was slated to go to a research facility, but somehow found themselves on the Rim.</baseDesc>
		<bodyTypeFemale>Female</bodyTypeFemale>
		<shuffleable>True</shuffleable>
		<slot>Childhood</slot>
		<spawnCategories>
			<li>NandroidGeneral</li>
			<li>NandroidSoldiers</li>
		</spawnCategories>
		<skillGains>
          <li>
            <key>Shooting</key>
            <value>1</value>
          </li>
          <li>
            <key>Melee</key>
            <value>1</value>
          </li>
		  <li>
            <key>Construction</key>
            <value>2</value>
          </li>
		  <li>
            <key>Mining</key>
            <value>1</value>
          </li>
		  <li>
            <key>Cooking</key>
            <value>5</value>
          </li>
		  <li>
            <key>Plants</key>
            <value>1</value>
          </li>
		  <li>
            <key>Animals</key>
            <value>1</value>
          </li>
		  <li>
            <key>Crafting</key>
            <value>2</value>
          </li>
		  <li>
            <key>Artistic</key>
            <value>3</value>
          </li>
		  <li>
            <key>Medicine</key>
            <value>4</value>
          </li>
		  <li>
            <key>Social</key>
            <value>6</value>
          </li>
		  <li>
            <key>Intellectual</key>
            <value>4</value>
          </li>
        </skillGains>
	</AlienRace.AlienBackstoryDef>
	
	<AlienRace.AlienBackstoryDef>
		<defName>NandroidMilspec</defName>
		<title>Milspec Nandroid</title>
		<titleShort>Mil-Nan</titleShort>
		<baseDesc>{PAWN_nameDef} is a Sterling brand Nandroid that is secretly built with military-grade specifications, but somehow found themselves on the Rim.</baseDesc>
		<bodyTypeFemale>Female</bodyTypeFemale>
		<shuffleable>True</shuffleable>
		<slot>Childhood</slot>
		<spawnCategories>
			<li>NandroidGeneral</li>
			<li>BadGurlz</li>
			<li>NandroidSoldiers</li>
		</spawnCategories>
		<skillGains>
          <li>
            <key>Shooting</key>
            <value>3</value>
          </li>
          <li>
            <key>Melee</key>
            <value>3</value>
          </li>
		  <li>
            <key>Construction</key>
            <value>3</value>
          </li>
		  <li>
            <key>Mining</key>
            <value>1</value>
          </li>
		  <li>
            <key>Cooking</key>
            <value>5</value>
          </li>
		  <li>
            <key>Plants</key>
            <value>1</value>
          </li>
		  <li>
            <key>Animals</key>
            <value>1</value>
          </li>
		  <li>
            <key>Crafting</key>
            <value>2</value>
          </li>
		  <li>
            <key>Artistic</key>
            <value>1</value>
          </li>
		  <li>
            <key>Medicine</key>
            <value>2</value>
          </li>
		  <li>
            <key>Social</key>
            <value>5</value>
          </li>
		  <li>
            <key>Intellectual</key>
            <value>2</value>
          </li>
        </skillGains>
	</AlienRace.AlienBackstoryDef>
	
	<AlienRace.AlienBackstoryDef>
		<defName>NandroidCustom1</defName>
		<title>Custom Nandroid</title>
		<titleShort>Custom Nan</titleShort>
		<baseDesc>{PAWN_nameDef} is a custom-made Sterling brand Nandroid that was slated to go to an Urbworld, but somehow found themselves on the Rim.</baseDesc>
		<bodyTypeFemale>Female</bodyTypeFemale>
		<shuffleable>True</shuffleable>
		<slot>Childhood</slot>
		<spawnCategories>
			<li>NandroidGeneral</li>
			<li>BadGurlz</li>
			<li>NandroidSoldiers</li>
		</spawnCategories>
		<skillGains>
          <li>
            <key>Shooting</key>
            <value>1</value>
          </li>
          <li>
            <key>Melee</key>
            <value>1</value>
          </li>
		  <li>
            <key>Construction</key>
            <value>2</value>
          </li>
		  <li>
            <key>Mining</key>
            <value>1</value>
          </li>
		  <li>
            <key>Cooking</key>
            <value>6</value>
          </li>
		  <li>
            <key>Plants</key>
            <value>3</value>
          </li>
		  <li>
            <key>Animals</key>
            <value>3</value>
          </li>
		  <li>
            <key>Crafting</key>
            <value>3</value>
          </li>
		  <li>
            <key>Artistic</key>
            <value>1</value>
          </li>
		  <li>
            <key>Medicine</key>
            <value>2</value>
          </li>
		  <li>
            <key>Social</key>
            <value>5</value>
          </li>
		  <li>
            <key>Intellectual</key>
            <value>2</value>
          </li>
        </skillGains>
	</AlienRace.AlienBackstoryDef>
	
	<AlienRace.AlienBackstoryDef>
		<defName>NandroidCustom2</defName>
		<title>Custom Nandroid</title>
		<titleShort>Custom Nan</titleShort>
		<baseDesc>{PAWN_nameDef} is a custom-made Sterling brand Nandroid that was slated to go to an Urbworld, but somehow found themselves on the Rim.</baseDesc>
		<bodyTypeFemale>Female</bodyTypeFemale>
		<shuffleable>True</shuffleable>
		<slot>Childhood</slot>
		<spawnCategories>
			<li>NandroidGeneral</li>
			<li>BadGurlz</li>
			<li>NandroidSoldiers</li>
		</spawnCategories>
		<skillGains>
          <li>
            <key>Shooting</key>
            <value>1</value>
          </li>
          <li>
            <key>Melee</key>
            <value>1</value>
          </li>
		  <li>
            <key>Construction</key>
            <value>2</value>
          </li>
		  <li>
            <key>Mining</key>
            <value>3</value>
          </li>
		  <li>
            <key>Cooking</key>
            <value>5</value>
          </li>
		  <li>
            <key>Plants</key>
            <value>1</value>
          </li>
		  <li>
            <key>Animals</key>
            <value>1</value>
          </li>
		  <li>
            <key>Crafting</key>
            <value>2</value>
          </li>
		  <li>
            <key>Artistic</key>
            <value>1</value>
          </li>
		  <li>
            <key>Medicine</key>
            <value>3</value>
          </li>
		  <li>
            <key>Social</key>
            <value>6</value>
          </li>
		  <li>
            <key>Intellectual</key>
            <value>2</value>
          </li>
        </skillGains>
	</AlienRace.AlienBackstoryDef>
	
	<AlienRace.AlienBackstoryDef>
		<defName>NandroidSalvaged</defName>
		<title>Salvaged Nandroid</title>
		<titleShort>Salvaged Nan</titleShort>
		<baseDesc>{PAWN_nameDef} is a Sterling brand Nandroid that was deemed outmoded and scrapped, but somebody had salvaged and reassembled them on the Rim.</baseDesc>
		<bodyTypeFemale>Female</bodyTypeFemale>
		<shuffleable>True</shuffleable>
		<slot>Childhood</slot>
		<spawnCategories>
			<li>NandroidGeneral</li>
			<li>BadGurlz</li>
			<li>NandroidSoldiers</li>
		</spawnCategories>
		<skillGains>
          <li>
            <key>Shooting</key>
            <value>2</value>
          </li>
          <li>
            <key>Melee</key>
            <value>2</value>
          </li>
		  <li>
            <key>Construction</key>
            <value>3</value>
          </li>
		  <li>
            <key>Mining</key>
            <value>1</value>
          </li>
		  <li>
            <key>Cooking</key>
            <value>4</value>
          </li>
		  <li>
            <key>Plants</key>
            <value>1</value>
          </li>
		  <li>
            <key>Animals</key>
            <value>1</value>
          </li>
		  <li>
            <key>Crafting</key>
            <value>2</value>
          </li>
		  <li>
            <key>Artistic</key>
            <value>1</value>
          </li>
		  <li>
            <key>Medicine</key>
            <value>1</value>
          </li>
		  <li>
            <key>Social</key>
            <value>4</value>
          </li>
		  <li>
            <key>Intellectual</key>
            <value>2</value>
          </li>
        </skillGains>
	</AlienRace.AlienBackstoryDef>

</Defs>